maxwelllink/__init__.py
maxwelllink/units.py
maxwelllink/em_solvers/__init__.py
maxwelllink/em_solvers/dummy_em.py
maxwelllink/em_solvers/laser_driven.py
maxwelllink/em_solvers/meep.py
maxwelllink/em_solvers/single_mode_cavity.py
maxwelllink/molecule/__init__.py
maxwelllink/molecule/molecule.py
maxwelllink/molecule/molecule_legacy.py
maxwelllink/mxl_drivers/__init__.py
maxwelllink/mxl_drivers/lammps/__init__.py
maxwelllink/mxl_drivers/lammps/fix_maxwelllink.cpp
maxwelllink/mxl_drivers/lammps/fix_maxwelllink.h
maxwelllink/mxl_drivers/lammps/install.py
maxwelllink/mxl_drivers/lammps/mxl_install_lammps.sh
maxwelllink/mxl_drivers/python/__init__.py
maxwelllink/mxl_drivers/python/mxl_driver.py
maxwelllink/mxl_drivers/python/models/__init__.py
maxwelllink/mxl_drivers/python/models/ase_model.py
maxwelllink/mxl_drivers/python/models/dummy_model.py
maxwelllink/mxl_drivers/python/models/qutip_model.py
maxwelllink/mxl_drivers/python/models/rt_ehrenfest_model.py
maxwelllink/mxl_drivers/python/models/rttddft_model.py
maxwelllink/mxl_drivers/python/models/tls_model.py
maxwelllink/sockets/__init__.py
maxwelllink/sockets/sockets.py
maxwelllink/tools/__init__.py
maxwelllink/tools/ir.py
maxwelllink/tools/pulses.py
maxwelllink/tools/tddft_spectrum.py
maxwelllink/tools/transverse_components.py
maxwelllink-0.3.0.dist-info/licenses/LICENSE
maxwelllink-0.3.0.dist-info/METADATA
maxwelllink-0.3.0.dist-info/WHEEL
maxwelllink-0.3.0.dist-info/entry_points.txt
maxwelllink-0.3.0.dist-info/top_level.txt
maxwelllink-0.3.0.dist-info/RECORD
