Metadata-Version: 2.4
Name: maxwelllink
Version: 0.3.0
Summary: MaxwellLink: A unified framework for self-consistent light-matter simulations
Author-email: "Tao E. Li" <taoeli@udel.edu>
License:                     GNU GENERAL PUBLIC LICENSE
Project-URL: Homepage, https://github.com/TaoELi/MaxwellLink
Project-URL: Documentation, https://taoeli.github.io/MaxwellLink
Project-URL: Source, https://github.com/TaoELi/MaxwellLink
Project-URL: Issues, https://github.com/TaoELi/MaxwellLink/issues
Keywords: electromagnetics,molecular-dynamics,quantum-simulation,socket-interface,light-matter,polariton
Classifier: Development Status :: 4 - Beta
Classifier: Intended Audience :: Science/Research
Classifier: License :: OSI Approved :: GNU General Public License v2 (GPLv2)
Classifier: Operating System :: OS Independent
Classifier: Programming Language :: Python
Classifier: Programming Language :: Python :: 3
Classifier: Programming Language :: Python :: 3.9
Classifier: Programming Language :: Python :: 3.10
Classifier: Programming Language :: Python :: 3.11
Classifier: Programming Language :: Python :: 3.12
Classifier: Programming Language :: Python :: 3.13
Classifier: Topic :: Scientific/Engineering :: Physics
Classifier: Topic :: Scientific/Engineering :: Chemistry
Requires-Python: >=3.9
License-File: LICENSE
Requires-Dist: numpy>=1.24
Requires-Dist: scipy>=1.10
Requires-Dist: cmake>=3.18
Requires-Dist: requests>=2.31
Provides-Extra: dev
Requires-Dist: pytest>=7; extra == "dev"
Requires-Dist: black>=24.3; extra == "dev"
Requires-Dist: flake8>=7.0; extra == "dev"
Requires-Dist: pre-commit>=3.6; extra == "dev"
Provides-Extra: docs
Requires-Dist: sphinx>=7.2; extra == "docs"
Requires-Dist: furo>=2024.1.29; extra == "docs"
Requires-Dist: sphinx-autodoc-typehints>=2.1; extra == "docs"
Requires-Dist: sphinxcontrib-napoleon>=0.7; extra == "docs"
Requires-Dist: myst-parser>=3.0; extra == "docs"
Requires-Dist: sphinx-copybutton>=0.5; extra == "docs"
Requires-Dist: sphinx-design>=0.6; extra == "docs"
Requires-Dist: nbsphinx>=0.9; extra == "docs"
Requires-Dist: sphinxcontrib-youtube; extra == "docs"
Requires-Dist: nbconvert; extra == "docs"
Requires-Dist: ipykernel; extra == "docs"
Requires-Dist: pandoc; extra == "docs"
Dynamic: license-file
